rutter/__init__.py
rutter/urlmap.py
rutter/tests/__init__.py
rutter/tests/test_urlmap.py
rutter-1.0.dist-info/LICENSE.txt
rutter-1.0.dist-info/METADATA
rutter-1.0.dist-info/WHEEL
rutter-1.0.dist-info/entry_points.txt
rutter-1.0.dist-info/top_level.txt
rutter-1.0.dist-info/RECORD
